tensorpack/__init__.py
tensorpack/libinfo.py
tensorpack/callbacks/__init__.py
tensorpack/callbacks/base.py
tensorpack/callbacks/concurrency.py
tensorpack/callbacks/graph.py
tensorpack/callbacks/group.py
tensorpack/callbacks/hooks.py
tensorpack/callbacks/inference.py
tensorpack/callbacks/inference_runner.py
tensorpack/callbacks/misc.py
tensorpack/callbacks/monitor.py
tensorpack/callbacks/param.py
tensorpack/callbacks/param_test.py
tensorpack/callbacks/prof.py
tensorpack/callbacks/saver.py
tensorpack/callbacks/stats.py
tensorpack/callbacks/steps.py
tensorpack/callbacks/summary.py
tensorpack/callbacks/trigger.py
tensorpack/compat/__init__.py
tensorpack/compat/tensor_spec.py
tensorpack/contrib/__init__.py
tensorpack/contrib/keras.py
tensorpack/dataflow/__init__.py
tensorpack/dataflow/base.py
tensorpack/dataflow/common.py
tensorpack/dataflow/format.py
tensorpack/dataflow/image.py
tensorpack/dataflow/parallel.py
tensorpack/dataflow/parallel_map.py
tensorpack/dataflow/raw.py
tensorpack/dataflow/remote.py
tensorpack/dataflow/serialize.py
tensorpack/dataflow/serialize_test.py
tensorpack/dataflow/dataset/__init__.py
tensorpack/dataflow/dataset/bsds500.py
tensorpack/dataflow/dataset/caltech101.py
tensorpack/dataflow/dataset/cifar.py
tensorpack/dataflow/dataset/ilsvrc.py
tensorpack/dataflow/dataset/mnist.py
tensorpack/dataflow/dataset/svhn.py
tensorpack/dataflow/imgaug/__init__.py
tensorpack/dataflow/imgaug/base.py
tensorpack/dataflow/imgaug/convert.py
tensorpack/dataflow/imgaug/crop.py
tensorpack/dataflow/imgaug/deform.py
tensorpack/dataflow/imgaug/external.py
tensorpack/dataflow/imgaug/geometry.py
tensorpack/dataflow/imgaug/imgaug_test.py
tensorpack/dataflow/imgaug/imgproc.py
tensorpack/dataflow/imgaug/meta.py
tensorpack/dataflow/imgaug/misc.py
tensorpack/dataflow/imgaug/noise.py
tensorpack/dataflow/imgaug/paste.py
tensorpack/dataflow/imgaug/transform.py
tensorpack/graph_builder/__init__.py
tensorpack/graph_builder/distributed.py
tensorpack/graph_builder/model_desc.py
tensorpack-0.10.1.dist-info/LICENSE
tensorpack-0.10.1.dist-info/METADATA
tensorpack-0.10.1.dist-info/WHEEL
tensorpack-0.10.1.dist-info/top_level.txt
tensorpack-0.10.1.dist-info/RECORD
