Metadata-Version: 2.1
Name: tensorpack
Version: 0.10.1
Summary: A Neural Network Training Interface on TensorFlow
Home-page: https://github.com/tensorpack/tensorpack
Author: TensorPack contributors
Author-email: ppwwyyxxc@gmail.com
License: Apache
Keywords: tensorflow,deep learning,neural network
Platform: UNKNOWN
Provides-Extra: all
